newio/__init__.py
newio/_socket.py
newio/api.py
newio/channel/__init__.py
newio/channel/asyncio_broker.py
newio/channel/asyncio_channel.py
newio/channel/error.py
newio/channel/newio_broker.py
newio/channel/thread_broker.py
newio/channel/thread_channel.py
newio/queue.py
newio/socket.py
newio/ssl.py
newio/sync.py
newio/syscall.py
newio-0.3.0.dist-info/WHEEL
newio-0.3.0.dist-info/METADATA
newio-0.3.0.dist-info/RECORD
