Metadata-Version: 2.1
Name: newio
Version: 0.3.0
Summary: Newio
Home-page: UNKNOWN
License: UNKOWN
Author: guyskk
Author-email: guyskk@qq.com
Requires-Python: >= 3.6.0.0
Classifier: Programming Language :: Python :: 3
Classifier: Programming Language :: Python :: 3.6
Classifier: Programming Language :: Python :: 3.7
